restretto/__init__.py
restretto/__main__.py
restretto/assertions.py
restretto/cli.py
restretto/errors.py
restretto/http.py
restretto/loader.py
restretto/rest.py
restretto/runner.py
restretto/utils.py
restretto-1.0.6.dist-info/LICENSE
restretto-1.0.6.dist-info/METADATA
restretto-1.0.6.dist-info/WHEEL
restretto-1.0.6.dist-info/entry_points.txt
restretto-1.0.6.dist-info/top_level.txt
restretto-1.0.6.dist-info/RECORD
