Metadata-Version: 2.1
Name: restretto
Version: 1.0.6
Summary: restretto is REST API testing tool
Home-page: http://github.com/wirewit/restretto
Author: Arthur Orlov
Author-email: feature.creature@gmail.com
License: UNKNOWN
Platform: UNKNOWN
Classifier: Development Status :: 5 - Production/Stable
Classifier: Environment :: Console
Classifier: Intended Audience :: Developers
Classifier: Operating System :: OS Independent
Classifier: Programming Language :: Python
Classifier: Programming Language :: Python :: 3
Classifier: Programming Language :: Python :: 3.3
Classifier: Programming Language :: Python :: 3.4
Classifier: Topic :: Internet :: WWW/HTTP
Classifier: Topic :: Software Development
Classifier: Topic :: Software Development :: Quality Assurance
Classifier: Topic :: Software Development :: Testing
Classifier: License :: OSI Approved :: Apache Software License
Requires-Dist: requests (>=2.7.0)
Requires-Dist: pyaml (>=3.11)
Requires-Dist: jinja2 (>=2.8)
Requires-Dist: clint (>=0.5)
